sqlai/__init__.py
sqlai/cli.py
sqlai/config.py
sqlai/helpers.py
sqlai/linting.py
sqlai/violations.py
sqlai-0.1.5.dist-info/METADATA
sqlai-0.1.5.dist-info/WHEEL
sqlai-0.1.5.dist-info/entry_points.txt
sqlai-0.1.5.dist-info/top_level.txt
sqlai-0.1.5.dist-info/RECORD
