Metadata-Version: 2.4
Name: sqlai
Version: 0.1.5
Summary: A command-line tool for SQL AI queries
Home-page: https://github.com/alexanderbrueck/sqlai
Author: Alexander Brück
License: MIT
Classifier: Programming Language :: Python :: 3
Classifier: License :: OSI Approved :: MIT License
Requires-Python: >=3.7
Requires-Dist: google-generativeai==0.8.5
Requires-Dist: tomli==2.2.1
Requires-Dist: tomli_w==1.2.0
Dynamic: author
Dynamic: classifier
Dynamic: description
Dynamic: home-page
Dynamic: license
Dynamic: requires-dist
Dynamic: requires-python
Dynamic: summary
